CHANGES.rst
nonlocalbox/__init__.py
nonlocalbox/exceptions.py
nonlocalbox/nonlocalbox.py
nonlocalbox/settings.py
nonlocalbox/version.py
nonlocalbox-0.1.dist-info/WHEEL
nonlocalbox-0.1.dist-info/METADATA
nonlocalbox-0.1.dist-info/LICENSE
nonlocalbox-0.1.dist-info/RECORD
