Metadata-Version: 2.1
Name: nonlocalbox
Version: 0.1
Summary: A friendly API for simulating nonlocal no-signalling correlations
Home-page: https://github.com/ohanyecz/nonlocalbox
License: GNU GPLv3
Author: Ottó Hanyecz
Requires-Python: >=3.8
Classifier: Development Status :: 5 - Production/Stable
Classifier: License :: OSI Approved :: MIT License
Classifier: License :: Other/Proprietary License
Classifier: Operating System :: OS Independent
Classifier: Programming Language :: Python :: 3
Classifier: Programming Language :: Python :: 3.8
Classifier: Programming Language :: Python :: 3.9
Classifier: Programming Language :: Python :: 3.10
Classifier: Programming Language :: Python :: 3.11
Classifier: Programming Language :: Python :: 3 :: Only
Classifier: Topic :: Scientific/Engineering :: Mathematics
Requires-Dist: requests (>=2.27.1)
Project-URL: Repository, https://github.com/ohanyecz/nonlocalbox
